cli/compact_main.py
cli/format_main.py
cli/main.py
nepali_num2word/__init__.py
nepali_num2word/core.py
nepali_num2word-0.2.3.dist-info/licenses/LICENSE
nepali_num2word-0.2.3.dist-info/METADATA
nepali_num2word-0.2.3.dist-info/WHEEL
nepali_num2word-0.2.3.dist-info/entry_points.txt
nepali_num2word-0.2.3.dist-info/top_level.txt
nepali_num2word-0.2.3.dist-info/RECORD
