Metadata-Version: 2.4
Name: nepali-num2word
Version: 0.2.3
Summary: Convert numbers to Nepali-style words and formatting
Home-page: https://github.com/kushal1o1/nepali-num2word
Author: Kushal
Author-email: Kushal <work.kusal@gmail.com>
License: MIT License
Project-URL: Homepage, https://github.com/kushal1o1/nepali-num2word
Project-URL: Bug Reports, https://github.com/kushal1o1/nepali-num2word/issues
Project-URL: Source, https://github.com/kushal1o1/nepali-num2word
Keywords: nepali,numbers,words,conversion,currency,formatting,unicode,devanagari
Classifier: Development Status :: 4 - Beta
Classifier: Intended Audience :: Developers
Classifier: License :: OSI Approved :: MIT License
Classifier: Operating System :: OS Independent
Classifier: Programming Language :: Python :: 3
Classifier: Programming Language :: Python :: 3.8
Classifier: Programming Language :: Python :: 3.9
Classifier: Programming Language :: Python :: 3.10
Classifier: Programming Language :: Python :: 3.11
Classifier: Programming Language :: Python :: 3.12
Classifier: Topic :: Software Development :: Libraries :: Python Modules
Classifier: Topic :: Text Processing :: Linguistic
Requires-Python: >=3.8
License-File: LICENSE
Provides-Extra: dev
Requires-Dist: pytest>=7.0.0; extra == "dev"
Requires-Dist: pytest-cov>=4.0.0; extra == "dev"
Dynamic: author
Dynamic: home-page
Dynamic: license-file
Dynamic: requires-python
